kvsh/__init__.py
kvsh/__main__.py
kvsh-0.1.2.dist-info/entry_points.txt
kvsh-0.1.2.dist-info/WHEEL
kvsh-0.1.2.dist-info/METADATA
kvsh-0.1.2.dist-info/RECORD
