Metadata-Version: 2.1
Name: kvsh
Version: 0.1.2
Summary: Persistent key-value store for the command line
Home-page: https://github.com/aatifsyed/kvsh
License: MIT
Author: Aatif Syed
Author-email: aatifsyedyp@gmail.com
Requires-Python: >=3.8,<4.0
Classifier: License :: OSI Approved :: MIT License
Classifier: Programming Language :: Python :: 3
Classifier: Programming Language :: Python :: 3.10
Classifier: Programming Language :: Python :: 3.8
Classifier: Programming Language :: Python :: 3.9
Requires-Dist: argcomplete (>=1.12.3,<2.0.0)
Requires-Dist: argparse (>=1.4.0,<2.0.0)
Requires-Dist: dataclasses-json (>=0.5.6,<0.6.0)
Requires-Dist: jsonschema (>=4.2.1,<5.0.0)
Requires-Dist: logging-actions (>=0.1.6,<0.2.0)
Requires-Dist: xdg (>=5.1.1,<6.0.0)
Project-URL: Repository, https://github.com/aatifsyed/kvsh
